dubler/__init__.py
dubler/_version.py
dubler/checksum.py
dubler/cli.py
dubler/config.py
dubler/state.py
dubler/sync.py
dubler-1.3.0.dist-info/METADATA
dubler-1.3.0.dist-info/WHEEL
dubler-1.3.0.dist-info/entry_points.txt
dubler-1.3.0.dist-info/top_level.txt
dubler-1.3.0.dist-info/RECORD
