Metadata-Version: 2.4
Name: dubler
Version: 1.3.0
Summary: Directory synchronization tool using checksums
Requires-Python: >=3.13
